django_stagesetting-0.5.0.dist-info/DESCRIPTION.rst
django_stagesetting-0.5.0.dist-info/LICENSE.txt
django_stagesetting-0.5.0.dist-info/METADATA
django_stagesetting-0.5.0.dist-info/RECORD
django_stagesetting-0.5.0.dist-info/WHEEL
django_stagesetting-0.5.0.dist-info/metadata.json
django_stagesetting-0.5.0.dist-info/top_level.txt
stagesetting/__init__.py
stagesetting/admin.py
stagesetting/apps.py
stagesetting/checks.py
stagesetting/context_processors.py
stagesetting/drf.py
stagesetting/forms.py
stagesetting/middleware.py
stagesetting/models.py
stagesetting/urls.py
stagesetting/utils.py
stagesetting/validators.py
stagesetting/views.py
stagesetting/widgets.py
stagesetting/migrations/0001_initial.py
stagesetting/migrations/__init__.py
stagesetting/templates/admin/stagesetting/add_form.html
stagesetting/templates/admin/stagesetting/change_form.html
stagesetting/templates/stagesetting/base.html
stagesetting/templates/stagesetting/create.html
stagesetting/templates/stagesetting/delete.html
stagesetting/templates/stagesetting/list.html
stagesetting/templates/stagesetting/update.html
stagesetting/templatetags/__init__.py
stagesetting/templatetags/stagesetting.py
