Metadata-Version: 2.0
Name: django-stagesetting
Version: 0.5.0
Summary: Dynamic runtime settings and configuration for Django sites
Home-page: https://github.com/kezabelle/django-stagesetting
Author: Keryn Knight
Author-email: python-package@kerynknight.com
License: BSD License
Download-URL: https://github.com/kezabelle/django-stagesetting/releases/tag/0.5.0
Keywords: settings,django,live,dynamic,utility
Platform: UNKNOWN
Classifier: Development Status :: 4 - Beta
Classifier: Intended Audience :: Developers
Classifier: License :: OSI Approved :: BSD License
Classifier: Environment :: Web Environment
Classifier: Topic :: Internet :: WWW/HTTP
Classifier: Programming Language :: Python
Classifier: Programming Language :: Python :: 2
Classifier: Programming Language :: Python :: 2.7
Classifier: Programming Language :: Python :: 3
Classifier: Programming Language :: Python :: 3.3
Classifier: Programming Language :: Python :: 3.4
Classifier: Programming Language :: Python :: 3.5
Classifier: Framework :: Django
Classifier: Framework :: Django :: 1.7
Classifier: Framework :: Django :: 1.8
Classifier: Framework :: Django :: 1.9
Classifier: Framework :: Django :: 1.10
Requires-Dist: Django (>=1.7)
